{"static":{"camera":{"label":"Camera 1"}},"sourceNumber":1,"sourceId":"Camera 1_1","timing":{"timecode":{"hours":0,"minutes":0,"seconds":6,"frames":22,"dropFrame":false,"format":{"frameRate":{"num":24,"denom":1}}},"mode":"tc","sampleTimecode":"00:00:06:22","sampleTime":"1970-01-01T00:00:14.403Z"},"lens":{"rawEncoders":{"focus":0,"iris":0,"zoom":3616},"pinholeFocalLength":3616,"fStop":0,"focusDistance":0},"protocol":{"name":"OpenTrackIO","version":[1,0,1]}}
{"static":{"camera":{"label":"Camera 1"}},"sourceNumber":1,"sourceId":"Camera 1_1","timing":{"timecode":{"hours":0,"minutes":0,"seconds":6,"frames":22,"dropFrame":false,"format":{"frameRate":{"num":24,"denom":1}}},"mode":"tc","sampleTimecode":"00:00:06:22","sampleTime":"1970-01-01T00:00:14.424Z"},"lens":{"rawEncoders":{"focus":0,"iris":0,"zoom":3598},"pinholeFocalLength":3598,"fStop":0,"focusDistance":0},"protocol":{"name":"OpenTrackIO","version":[1,0,1]}}
